mail.py
securekeyz-0.1.dist-info/METADATA
securekeyz-0.1.dist-info/WHEEL
securekeyz-0.1.dist-info/entry_points.txt
securekeyz-0.1.dist-info/top_level.txt
securekeyz-0.1.dist-info/RECORD
