Metadata-Version: 2.1
Name: securekeyz
Version: 0.1
Summary: SecureKeyz is a Python-based command-line tool designed to help you securely manage your API keys. It allows you to store, modify, and transfer API keys between different services while keeping them encrypted.
Author: hasan
Author-email: hasanfq818@gmail.com
License: MIT
Classifier: Programming Language :: Python :: 3
Classifier: License :: OSI Approved :: MIT License
Classifier: Operating System :: OS Independent
Requires-Python: >=3.6
Requires-Dist: argparse ==1.4.0
Requires-Dist: prompt-toolkit ==3.0.43
